{   
    "selector_variables": ["@a", "@e", "@r", "@p", "@s"],

    "selector_arguments": [
        "x", "y", "z", "dx", "dy", "dz", "r", "rm", "rx", "rxm", "ry", "rym",
        "c", "l", "lm", "team", "name", "tag", "type", "m",
        "distance", "level", "x_rotation", "y_rotation"
    ],

    "selector_replacements": {
        "dist": "distance",
        "xrot": "x_rotation",
        "yrot": "y_rotation",
        "lvl": "level"
    },

    "selector_argument_details": {
        "x": {
            "parse_type": "SIGNED_INT"
        },
        "y": {
            "parse_type": "SIGNED_INT"
        },
        "z": {
            "parse_type": "SIGNED_INT"
        },
        "dx": {
            "parse_type": "SIGNED_INT"
        },
        "dy": {
            "parse_type": "SIGNED_INT"
        },
        "dz": {
            "parse_type": "SIGNED_INT"
        },
        "r": {
            "parse_type": "SHORTCUT_ERROR"
        },
        "rm": {
            "parse_type": "SHORTCUT_ERROR"
        },
        "rx": {
            "parse_type": "SHORTCUT_ERROR"
        },
        "rxm": {
            "parse_type": "SHORTCUT_ERROR"
        },
        "ry": {
            "parse_type": "SHORTCUT_ERROR"
        },
        "rym": {
            "parse_type": "SHORTCUT_ERROR"
        },

        "c": {
            "parse_type": "SIGNED_INT"
        },
        "l": {
            "parse_type": "SHORTCUT_ERROR"
        },
        "lm": {
            "parse_type": "SHORTCUT_ERROR"
        },

        "team": {
            "parse_type": "STR"
        },
        "name": {
            "parse_type": "STR"
        },

        "tag": {
            "parse_type": "SHORTCUT_ERROR"
        },

        "distance": {
            "parse_type": "INT_RANGE",
            "range_replace": ["rm", "r"]
        },
        "x_rotation": {
            "parse_type": "INT_RANGE",
            "range_replace": ["rx", "rxm"]
        },
        "y_rotation": {
            "parse_type": "INT_RANGE",
            "range_replace": ["ry", "rym"]
        },
        "level": {
            "parse_type": "INT_RANGE",
            "range_replace": ["l", "lm"]
        },

        "m": {
            "parse_type": "VALUES",
            "values": ["0", "1", "2", "3"]
        },

        "type": {
            "parse_type": "ENTITIES"
        }
    }
}